amazon.ion-0.13.0-py3.9-nspkg.pth
amazon/ion/writer_buffer.py
amazon/ion/equivalence.py
amazon/ion/simpleion.py
amazon/ion/ioncmodule.c
amazon/ion/writer_text.py
amazon/ion/reader_text.py
amazon/ion/exceptions.py
amazon/ion/util.py
amazon/ion/simple_types.py
amazon/ion/__init__.py
amazon/ion/core.py
amazon/ion/json_encoder.py
amazon/ion/writer_binary.py
amazon/ion/symbols.py
amazon/ion/sliceable_buffer.py
amazon/ion/writer_binary_raw.py
amazon/ion/ionc.cpython-39-aarch64-linux-gnu.so
amazon/ion/reader_binary.py
amazon/ion/reader.py
amazon/ion/reader_managed.py
amazon/ion/writer_binary_raw_fields.py
amazon/ion/writer.py
amazon/ion/_ioncmodule.h
amazon/ion/ion-c-build/include/ionc/ion_types.h
amazon/ion/ion-c-build/include/ionc/ion_catalog.h
amazon/ion/ion-c-build/include/ionc/ion_int.h
amazon/ion/ion-c-build/include/ionc/ion_decimal.h
amazon/ion/ion-c-build/include/ionc/ion_string.h
amazon/ion/ion-c-build/include/ionc/ion_symbol_table.h
amazon/ion/ion-c-build/include/ionc/ion_writer.h
amazon/ion/ion-c-build/include/ionc/ion_stream.h
amazon/ion/ion-c-build/include/ionc/ion_debug.h
amazon/ion/ion-c-build/include/ionc/ion_collection.h
amazon/ion/ion-c-build/include/ionc/ion_float.h
amazon/ion/ion-c-build/include/ionc/ion_platform_config.h
amazon/ion/ion-c-build/include/ionc/ion_error_codes.h
amazon/ion/ion-c-build/include/ionc/ion_timestamp.h
amazon/ion/ion-c-build/include/ionc/ion_reader.h
amazon/ion/ion-c-build/include/ionc/ion_errors.h
amazon/ion/ion-c-build/include/ionc/ion_extractor.h
amazon/ion/ion-c-build/include/ionc/ion.h
amazon/ion/ion-c-build/include/ionc/ion_version.h
amazon/ion/ion-c-build/include/decNumber/decimal64.h
amazon/ion/ion-c-build/include/decNumber/decDouble.h
amazon/ion/ion-c-build/include/decNumber/decPacked.h
amazon/ion/ion-c-build/include/decNumber/decimal32.h
amazon/ion/ion-c-build/include/decNumber/decContext.h
amazon/ion/ion-c-build/include/decNumber/decimal128.h
amazon.ion-0.13.0.dist-info/top_level.txt
amazon.ion-0.13.0.dist-info/RECORD
amazon.ion-0.13.0.dist-info/LICENSE
amazon.ion-0.13.0.dist-info/NOTICE
amazon.ion-0.13.0.dist-info/METADATA
amazon.ion-0.13.0.dist-info/WHEEL
amazon.ion-0.13.0.dist-info/namespace_packages.txt
