Metadata-Version: 2.1
Name: amazon.ion
Version: 0.13.0
Summary: A Python implementation of Amazon Ion.
Home-page: http://github.com/amazon-ion/ion-python
Author: Amazon Ion Team
Author-email: ion-team@amazon.com
License: Apache License 2.0
Platform: UNKNOWN
License-File: LICENSE
License-File: NOTICE
